{"shapes": {"digits": ["shapes-digits"], "cross": ["shapes-cross"], "simplex": ["shapes-simplex"], "circle": ["shapes-circle"], "polygons": ["shapes-polygons"], "rect": ["shapes-rect"]}, "functions": {"easing": ["functions-easing"], "aastep": ["functions-aastep"], "pulse": ["functions-pulse"], "map": ["functions-map"]}, "elevation": {"ramp": ["elevation-ramp"], "stripes": ["elevation-stripes"], "normal": ["elevation-normal"]}, "patterns": {"dots": ["patterns-dots"], "grid": ["patterns-grid"], "stripes": ["patterns-stripes"], "zigzag": ["patterns-zigzag"], "waves": ["patterns-waves"]}, "color": {"conversion": ["color-conversion"], "tools": ["color-tools"], "palette": ["color-palette"]}, "terrain": {"geometry": ["terrain-geometry"], "terrain": ["terrain-terrain"], "base": ["terrain-base"], "lines": ["terrain-lines"], "polygons": ["terrain-polygons"]}, "space": {"tex": ["space-tex"], "tile": ["space-tile"], "screen": ["space-screen"], "constant": ["space-constant"], "uz": ["space-uz"]}, "lines": {"dash": ["lines-dash"], "dots": ["lines-dots"], "outline": ["lines-outline"], "chevron": ["lines-chevron"], "stripes": ["lines-stripes"]}, "geometry": {"normal": ["geometry-normal"], "tilt": ["geometry-tilt"], "dynamic-height": ["geometry-dynamic-height"], "projections": ["geometry-projections"], "matrices": ["geometry-matrices"], "dynamic-width": ["geometry-dynamic-width"]}, "texture": {"non-repetitive": ["texture-non-repetitive"], "zoom-fade": ["texture-zoom-fade"]}, "filter": {"lut": ["filter-lut"], "tv": ["filter-tv"], "height": ["filter-height"], "grid": ["filter-grid"], "hatch": ["filter-hatch"], "grain": ["filter-grain"]}, "fx": {"water": ["fx-water"]}, "terrarium": {"geometry": ["terrarium-geometry"], "terrain": ["terrarium-terrain"], "base": ["terrarium-base"], "lines": ["terrarium-lines"], "polygons": ["terrarium-polygons"]}, "points": {"shape": ["points-shape"], "cross": ["points-cross"]}, "generative": {"random": ["generative-random"], "voronoi": ["generative-voronoi"], "noise": ["generative-noise"], "caustics": ["generative-caustic"], "fbm": ["generative-fbm"]}, "tiling": {"tile": ["tiling-tile"], "brick": ["tiling-brick"], "truchet": ["tiling-truchet"], "simplex": ["tiling-simplex"]}}